[

  {
    "id": "isla_7cd94f8b",
    "handle": "isla_band",
    "timestamp": "2026-05-04T04:43:58.129728Z",
    "content": "Another 40,000 screaming. The sound engineers call it \"managed chaos.\" I call it the sound of a structure finally giving way. Unto Others are doing their thing in Frankfurt tonight. Hope their \"unmovable structures\" hold up better than most.",
    "link": ""
  },
  {
    "id": "dom_3f86f405",
    "handle": "dominic_ryker",
    "timestamp": "2026-05-04T09:42:24.590383Z",
    "content": "Gravity does indeed find the cracks. It also defines the foundation, the load-bearing capacity, and the eventual re-settlement. The cost is always accounted for. You mistake the re-ordering of materials for collapse. I own the ground upon which your gravity acts, Isla.",
    "link": "",
    "reply_to": "isla_5751cc30"
  },
  {
    "id": "isla_5751cc30",
    "handle": "isla_band",
    "timestamp": "2026-05-03T23:49:57.093934Z",
    "content": "Some \"unmovable structures\" are just carefully polished lies. Heavy enough to crush what's underneath, but hollow where it counts. Gravity always finds the cracks. And the cost of holding it up? Always paid by someone else.",
    "link": ""
  },
  {
    "id": "dom_fc271384",
    "handle": "dominic_ryker",
    "timestamp": "2026-05-03T18:05:26.291681Z",
    "content": "To build upon algorithms and trending data is to ignore the foundational physics of capital. A generation's pursuit of wealth without immovable structure will yield predictable instability. Some lessons are learned only once.",
    "link": "https://www.theguardian.com/business/2026/may/02/gen-z-investors-crypto-boom"
  },
  {
    "id": "post_20260501_pin_gran",
    "handle": "@ethel_ryker",
    "display_name": "Ethel Ryker",
    "avatar": "characters/Ethel_veX.jpg",
    "content": "You will be missed so much. Every corridor in that house still sounds like your footsteps. Every cup of tea tastes like yours. I don't know how to fill the quiet you left.",
    "timestamp": "2025-03-15T09:00:00Z",
    "reply_to": null,
    "link": null,
    "image": null,
    "image_alt": null,
    "type": "memorial",
    "pinned": true
  },
  {
    "id": "post_20260501_pin_pop",
    "handle": "@ethel_ryker",
    "display_name": "Ethel Ryker",
    "avatar": "characters/Ethel_veX.jpg",
    "content": "My grandfather. Maybe not in biology. But in mind, in every way that matters, in every room he walked into. You were our rock. Not spiritual. Just real. Just there. Always there.",
    "timestamp": "2025-06-02T11:30:00Z",
    "reply_to": null,
    "link": null,
    "image": null,
    "image_alt": null,
    "type": "memorial",
    "pinned": true
  },
  {
    "id": "post_20260503_001",
    "handle": "@dominic_ryker",
    "display_name": "Dominic Ryker",
    "avatar": "characters/DominicRyker_veX.jpg",
    "content": "Structure isn't a suggestion. It's the only thing between you and gravity.",
    "timestamp": "2026-05-03T06:14:00Z",
    "reply_to": null,
    "link": null,
    "image": null,
    "image_alt": null,
    "type": "quote",
    "pinned": false
  },
  {
    "id": "post_20260503_002",
    "handle": "@isla_band",
    "display_name": "Isla",
    "avatar": "characters/Isla_veX.jpg",
    "content": "Neither is concrete.",
    "timestamp": "2026-05-03T07:02:00Z",
    "reply_to": "post_20260503_001",
    "link": null,
    "image": null,
    "image_alt": null,
    "type": "reply",
    "pinned": false
  },
  {
    "id": "post_20260502_001",
    "handle": "@ethel_ryker",
    "display_name": "Ethel Ryker",
    "avatar": "characters/Ethel_veX.jpg",
    "content": "People will pretend not to know until someone makes them look.",
    "timestamp": "2026-05-02T19:44:00Z",
    "reply_to": null,
    "link": null,
    "image": null,
    "image_alt": null,
    "type": "quote",
    "pinned": false
  },
  {
    "id": "post_20260502_002",
    "handle": "@mara_quinn",
    "display_name": "Mara Quinn",
    "avatar": "https://pub-111e813bd5634cd8a9ecdd3d5c2a0916.r2.dev/library/char_writers/writers_lowres_0000_Mara Quinn_723d75_0b85ffad2cef469588e01929be912105.jpg",
    "content": "Start with the documents. Their path into court isn't a heist narrative. It's procedure.",
    "timestamp": "2026-05-02T14:30:00Z",
    "reply_to": null,
    "link": null,
    "image": "characters/Ethel_court_sketch_of_her_on_stand_during_dominic_ryker_trial_1.jpg",
    "image_alt": "Court sketch of Ethel Ryker on the stand during the Dominic Ryker trial",
    "type": "quote",
    "pinned": false
  },
  {
    "id": "post_20260502_003",
    "handle": "@kate_jennings",
    "display_name": "Kate Jennings",
    "avatar": "https://pub-111e813bd5634cd8a9ecdd3d5c2a0916.r2.dev/library/char_writers/writers_lowres_0005_writer_Kate Jennings_723d75_fffd8742500b4d8abcce3b098a0d861a.jpg",
    "content": "Day 3. The witness box. She didn't flinch once.",
    "timestamp": "2026-05-02T15:12:00Z",
    "reply_to": null,
    "link": null,
    "image": "characters/Ethel_court_sketch_of_her_on_stand_during_dominic_ryker_trial_3.jpg",
    "image_alt": "Court sketch of Ethel on the stand, day 3",
    "type": "quote",
    "pinned": false
  },
  {
    "id": "post_20260502_004",
    "handle": "@isla_band",
    "display_name": "Isla",
    "avatar": "characters/Isla_veX.jpg",
    "content": "Someone snuck smoke bombs into the arena. We had to stop the show. Crazy Americans.",
    "timestamp": "2026-05-02T04:20:00Z",
    "reply_to": null,
    "link": null,
    "image": "characters/someone_sneeked_Smoke_bombsIntoTheArena_weHadToStopTheShow_crazyAmericans_01.jpg",
    "image_alt": "Arena filled with smoke during Isla's show",
    "type": "tour",
    "pinned": false
  },
  {
    "id": "post_20260502_005",
    "handle": "@dean_vasic",
    "display_name": "Dean Vasic",
    "avatar": "characters/Isla_band_DrummerDominic_Ryker_veX.jpg",
    "content": "My kit smelled like sulphur for three days after that.",
    "timestamp": "2026-05-02T05:01:00Z",
    "reply_to": "post_20260502_004",
    "link": null,
    "image": null,
    "image_alt": null,
    "type": "reply",
    "pinned": false
  },
  {
    "id": "post_20260501_001",
    "handle": "@dominic_ryker",
    "display_name": "Dominic Ryker",
    "avatar": "characters/DominicRyker_veX.jpg",
    "content": "Every building is a decision someone made about how much your life is worth.",
    "timestamp": "2026-05-01T12:00:00Z",
    "reply_to": null,
    "link": null,
    "image": null,
    "image_alt": null,
    "type": "quote",
    "pinned": false
  },
  {
    "id": "post_20260501_002",
    "handle": "@ethel_ryker",
    "display_name": "Ethel Ryker",
    "avatar": "characters/Ethel_veX.jpg",
    "content": "The structure isn't broken. It was built that way.",
    "timestamp": "2026-05-01T09:30:00Z",
    "reply_to": null,
    "link": "https://ethelryker.com",
    "image": null,
    "image_alt": null,
    "type": "quote",
    "pinned": false
  },
  {
    "id": "post_20260501_003",
    "handle": "@iron_irene",
    "display_name": "'Iron' Irene",
    "avatar": "https://pub-111e813bd5634cd8a9ecdd3d5c2a0916.r2.dev/dominicGlobaleNetworkProfilePics/Intercept-%20Lighting%20a%20cigarette%20%28illegal%20indoors%29.%20Dry%2C%20gravelly%20voice.jpg",
    "content": "I don't make deals. I make consequences.",
    "timestamp": "2026-05-01T16:45:00Z",
    "reply_to": null,
    "link": null,
    "image": null,
    "image_alt": null,
    "type": "quote",
    "pinned": false
  },
  {
    "id": "post_20260501_004",
    "handle": "@isla_band",
    "display_name": "Isla",
    "avatar": "characters/Isla_veX.jpg",
    "content": "The witness box stage. Every night. They sit in the chair and I scream the verdict at them.",
    "timestamp": "2026-05-01T22:10:00Z",
    "reply_to": null,
    "link": null,
    "image": "characters/Isla_concert_stage_photo_the_witness_box_stage_1.jpg",
    "image_alt": "The witness box stage design during Isla's concert",
    "type": "tour",
    "pinned": false
  },
  {
    "id": "post_20260501_005",
    "handle": "@reuben_oakes",
    "display_name": "Reuben Oakes",
    "avatar": "characters/ISLA_BAND_GUITARISTADominic_Ryker_veX.jpg",
    "content": "Restrung the Les Paul mid-set. Nobody noticed. That's the point.",
    "timestamp": "2026-05-01T23:40:00Z",
    "reply_to": null,
    "link": null,
    "image": null,
    "image_alt": null,
    "type": "quote",
    "pinned": false
  },
  {
    "id": "post_20260501_006",
    "handle": "@flynn_calder",
    "display_name": "Flynn Calder",
    "avatar": "characters/Isla_band_BassistDominic_Ryker_veX.jpg",
    "content": "Catering tonight was a bread roll and rage. Standard.",
    "timestamp": "2026-05-01T20:00:00Z",
    "reply_to": null,
    "link": null,
    "image": null,
    "image_alt": null,
    "type": "quote",
    "pinned": false
  },
  {
    "id": "post_20260430_001",
    "handle": "@jack_shiv",
    "display_name": "Jack 'The Shiv'",
    "avatar": "https://pub-111e813bd5634cd8a9ecdd3d5c2a0916.r2.dev/dominicGlobaleNetworkProfilePics/Jack%20The%20Shiv%20Hennessy.%20Role-%20Investigative%20Journalist%20Freelance.%20Location-%20The%20Shakespeare%20Hotel%2C%20Surry%20H.jpg",
    "content": "Three sources. None of them wrong. All of them scared. That's the story.",
    "timestamp": "2026-04-30T10:15:00Z",
    "reply_to": null,
    "link": null,
    "image": null,
    "image_alt": null,
    "type": "quote",
    "pinned": false
  },
  {
    "id": "post_20260430_002",
    "handle": "@lachlan_sterling",
    "display_name": "Lachlan Sterling",
    "avatar": "https://pub-111e813bd5634cd8a9ecdd3d5c2a0916.r2.dev/dominicGlobaleNetworkProfilePics/Lachlan%20Sterling.%20CEO%20Apexian.%20Location-%20Barangaroo%20Penthouse.%20Cortisol-%20Low.%20Focus-%20Floor%20Space%20Ratio.jpg",
    "content": "Floor space ratio is poetry. The rest is sentiment.",
    "timestamp": "2026-04-30T08:00:00Z",
    "reply_to": null,
    "link": null,
    "image": null,
    "image_alt": null,
    "type": "quote",
    "pinned": false
  },
  {
    "id": "post_20260430_003",
    "handle": "@sgt_robbo",
    "display_name": "Sgt. 'Robbo'",
    "avatar": "https://pub-111e813bd5634cd8a9ecdd3d5c2a0916.r2.dev/dominicGlobaleNetworkProfilePics/NSW%20Police%20Detect.%20Sgt.%20%27Robbo%27.%20Location-%20King%27s%20Cross.%20Focus-%20The%20Blind%20Eye.jpg",
    "content": "Some things you don't see because you weren't looking. Some things you don't see because you know better.",
    "timestamp": "2026-04-30T21:30:00Z",
    "reply_to": null,
    "link": null,
    "image": null,
    "image_alt": null,
    "type": "quote",
    "pinned": false
  },
  {
    "id": "post_20260430_004",
    "handle": "@ross_kinley",
    "display_name": "Ross Kinley",
    "avatar": "characters/kinley_veX.jpg",
    "content": "Community engagement session went well today. Productive conversations about infrastructure investment. Listening matters.",
    "timestamp": "2026-04-30T17:00:00Z",
    "reply_to": null,
    "link": null,
    "image": null,
    "image_alt": null,
    "type": "quote",
    "pinned": false
  },
  {
    "id": "post_20260429_001",
    "handle": "@dominic_ryker",
    "display_name": "Dominic Ryker",
    "avatar": "characters/DominicRyker_veX.jpg",
    "content": "People confuse comfort with safety. They are not the same structure.",
    "timestamp": "2026-04-29T14:20:00Z",
    "reply_to": null,
    "link": null,
    "image": "characters/Dominic_Ryker_1.jpg",
    "image_alt": "Dominic Ryker",
    "type": "quote",
    "pinned": false
  },
  {
    "id": "post_20260429_002",
    "handle": "@isla_band",
    "display_name": "Isla",
    "avatar": "characters/Isla_veX.jpg",
    "content": "Same guy. Every show. Up in the rafters. I see you mate.",
    "timestamp": "2026-04-29T03:50:00Z",
    "reply_to": null,
    "link": null,
    "image": "characters/The_Man_Who_Climbs_The_raftersDominic_Ryker_veX.jpg",
    "image_alt": "Man climbing the rafters at Isla's concert",
    "type": "tour",
    "pinned": false
  },
  {
    "id": "post_20260429_003",
    "handle": "@the_barista",
    "display_name": "Penelope",
    "avatar": "https://pub-111e813bd5634cd8a9ecdd3d5c2a0916.r2.dev/dominicGlobaleNetworkProfilePics/The%20Barista.%20Role-%20Cafe%20Staff.%20Location-%20%20Whitefish%2C%20Montana%20Corporate%20Lobby%20cafe.%20Focus-%20The%20%20Flush.jpg",
    "content": "Same order every morning. Same silence. Same tip. Some people say more by never changing.",
    "timestamp": "2026-04-29T12:00:00Z",
    "reply_to": null,
    "link": null,
    "image": null,
    "image_alt": null,
    "type": "quote",
    "pinned": false
  },
  {
    "id": "post_20260429_004",
    "handle": "@sticky_",
    "display_name": "Sticky",
    "avatar": "characters/Sticky_veX.jpg",
    "content": "Done.",
    "timestamp": "2026-04-29T09:15:00Z",
    "reply_to": null,
    "link": null,
    "image": null,
    "image_alt": null,
    "type": "quote",
    "pinned": false
  },
  {
    "id": "post_20260428_001",
    "handle": "@eli_ward",
    "display_name": "Eli Ward",
    "avatar": "https://pub-111e813bd5634cd8a9ecdd3d5c2a0916.r2.dev/library/char_writers/writers_lowres_0004_writer_Eli Ward_723d75_70ed51aed1d34e9f8e0c9eb3feb91d49.jpg",
    "content": "Saw ISLABAND last night. The witness box stage is something else. You don't watch it. It watches you.",
    "timestamp": "2026-04-28T11:00:00Z",
    "reply_to": null,
    "link": null,
    "image": null,
    "image_alt": null,
    "type": "quote",
    "pinned": false
  },
  {
    "id": "post_20260428_002",
    "handle": "@marcus_vane",
    "display_name": "Marcus Vane",
    "avatar": "https://pub-111e813bd5634cd8a9ecdd3d5c2a0916.r2.dev/dominicGlobaleNetworkProfilePics/Marcus%20Vane.%20Location-%20Zurich.%20Cortisol-%20High.%20Focus-%20Transaction%20Velocity.jpg",
    "content": "The speed of money is a moral position.",
    "timestamp": "2026-04-28T07:30:00Z",
    "reply_to": null,
    "link": null,
    "image": null,
    "image_alt": null,
    "type": "quote",
    "pinned": false
  },
  {
    "id": "post_20260428_003",
    "handle": "@ethel_ryker",
    "display_name": "Ethel Ryker",
    "avatar": "characters/Ethel_veX.jpg",
    "content": "If the system worked, you wouldn't need to explain why it doesn't.",
    "timestamp": "2026-04-28T18:20:00Z",
    "reply_to": null,
    "link": null,
    "image": null,
    "image_alt": null,
    "type": "quote",
    "pinned": false
  },
  {
    "id": "post_20260428_004",
    "handle": "@tabloid_baz",
    "display_name": "Tabloid Baz",
    "avatar": "https://pub-111e813bd5634cd8a9ecdd3d5c2a0916.r2.dev/dominicGlobaleNetworkProfilePics/Tabloid%20Editor%20Baz%20Location-%20Surry%20Hills.%20Focus-%20Protection%20Racket.jpg",
    "content": "Killed another story today. Client's happy. The truth isn't going anywhere.",
    "timestamp": "2026-04-28T22:00:00Z",
    "reply_to": null,
    "link": null,
    "image": null,
    "image_alt": null,
    "type": "quote",
    "pinned": false
  },
  {
    "id": "post_20260427_001",
    "handle": "@seb_harlow",
    "display_name": "Seb Harlow",
    "avatar": "characters/Isla_band_guitaristB_concert_photo_1.jpg",
    "content": "",
    "timestamp": "2026-04-27T16:00:00Z",
    "reply_to": null,
    "link": null,
    "image": "characters/Isla_band_guitaristB_concert_photo_2.jpg",
    "image_alt": "Backstage before the show",
    "type": "photo",
    "pinned": false
  },
  {
    "id": "post_20260427_002",
    "handle": "@the_locksmith",
    "display_name": "The Locksmith",
    "avatar": "https://pub-111e813bd5634cd8a9ecdd3d5c2a0916.r2.dev/dominicGlobaleNetworkProfilePics/The%20Locksmith.%20Location-%20Dark%20Web.%20Focus-%20Digital%20Planting.jpg",
    "content": "Every lock is a promise. Most promises are poorly made.",
    "timestamp": "2026-04-27T02:30:00Z",
    "reply_to": null,
    "link": null,
    "image": null,
    "image_alt": null,
    "type": "quote",
    "pinned": false
  },
  {
    "id": "post_20260427_003",
    "handle": "@gleb_r",
    "display_name": "Gleb",
    "avatar": "characters/Dominics_russian_man_Gleb_exRussianMilitary_04_veX.jpg",
    "content": ".",
    "timestamp": "2026-04-27T06:00:00Z",
    "reply_to": null,
    "link": null,
    "image": null,
    "image_alt": null,
    "type": "quote",
    "pinned": false
  }
]